{
	"name": "GL304000",
	"graphName": "PX.Objects.GL.JournalWithSubEntry",
	"primaryView": "BatchModule",
	"showUDFIndicator": true,
	"featureInstalled": [],
	"actions": [],
	"views": [
		{
			"name": "BatchModule",
			"dacClassName": null,
			"displayName": null,
			"isCollection": false,
			"featureInstalled": [],
			"fields": [
				{
					"args": null,
					"stateType": "default",
					"name": "BatchNbr",
					"bound": true,
					"commitChanges": false,
					"suppressLabel": false,
					"invisible": false,
					"readonly": false,
					"disabled": false,
					"multiLine": false,
					"calculated": false,
					"linkCommand": null,
					"text": null,
					"group": null,
					"placeBeforeProperty": null,
					"placeAfterProperty": null,
					"decorators": [],
					"editorType": null
				},
				{
					"args": [
						32
					],
					"stateType": "default",
					"name": "Status",
					"bound": true,
					"commitChanges": false,
					"suppressLabel": false,
					"invisible": false,
					"readonly": false,
					"disabled": true,
					"multiLine": false,
					"calculated": false,
					"linkCommand": null,
					"text": null,
					"group": null,
					"placeBeforeProperty": null,
					"placeAfterProperty": null,
					"decorators": [],
					"editorType": null
				},
				{
					"args": [
						16
					],
					"stateType": "default",
					"name": "DateEntered",
					"bound": true,
					"commitChanges": true,
					"suppressLabel": false,
					"invisible": false,
					"readonly": false,
					"disabled": false,
					"multiLine": false,
					"calculated": false,
					"linkCommand": null,
					"text": null,
					"group": null,
					"placeBeforeProperty": null,
					"placeAfterProperty": null,
					"decorators": [],
					"editorType": null
				},
				{
					"args": [
						16
					],
					"stateType": "default",
					"name": "FinPeriodID",
					"bound": true,
					"commitChanges": true,
					"suppressLabel": false,
					"invisible": false,
					"readonly": false,
					"disabled": false,
					"multiLine": false,
					"calculated": false,
					"linkCommand": null,
					"text": null,
					"group": null,
					"placeBeforeProperty": null,
					"placeAfterProperty": null,
					"decorators": [],
					"editorType": null
				},
				{
					"args": [
						16
					],
					"stateType": "default",
					"name": "BranchID",
					"bound": true,
					"commitChanges": true,
					"suppressLabel": false,
					"invisible": false,
					"readonly": false,
					"disabled": false,
					"multiLine": false,
					"calculated": false,
					"linkCommand": null,
					"text": null,
					"group": null,
					"placeBeforeProperty": null,
					"placeAfterProperty": null,
					"decorators": [],
					"editorType": null
				},
				{
					"args": [
						32
					],
					"stateType": "default",
					"name": "LedgerID",
					"bound": true,
					"commitChanges": false,
					"suppressLabel": false,
					"invisible": false,
					"readonly": false,
					"disabled": true,
					"multiLine": false,
					"calculated": false,
					"linkCommand": null,
					"text": null,
					"group": null,
					"placeBeforeProperty": null,
					"placeAfterProperty": null,
					"decorators": [],
					"editorType": null
				},
				{
					"args": null,
					"stateType": "default",
					"name": "CuryID",
					"bound": true,
					"commitChanges": false,
					"suppressLabel": false,
					"invisible": false,
					"readonly": false,
					"disabled": false,
					"multiLine": false,
					"calculated": false,
					"linkCommand": null,
					"text": null,
					"group": null,
					"placeBeforeProperty": null,
					"placeAfterProperty": null,
					"decorators": [],
					"editorType": null
				},
				{
					"args": null,
					"stateType": "default",
					"name": "CuryInfoID",
					"bound": true,
					"commitChanges": false,
					"suppressLabel": false,
					"invisible": false,
					"readonly": false,
					"disabled": false,
					"multiLine": false,
					"calculated": false,
					"linkCommand": null,
					"text": null,
					"group": null,
					"placeBeforeProperty": null,
					"placeAfterProperty": null,
					"decorators": [],
					"editorType": null
				},
				{
					"args": null,
					"stateType": "default",
					"name": "Description",
					"bound": true,
					"commitChanges": false,
					"suppressLabel": false,
					"invisible": false,
					"readonly": false,
					"disabled": false,
					"multiLine": false,
					"calculated": false,
					"linkCommand": null,
					"text": null,
					"group": null,
					"placeBeforeProperty": null,
					"placeAfterProperty": null,
					"decorators": [],
					"editorType": null
				},
				{
					"args": [
						32
					],
					"stateType": "default",
					"name": "CuryDebitTotal",
					"bound": true,
					"commitChanges": false,
					"suppressLabel": false,
					"invisible": false,
					"readonly": false,
					"disabled": true,
					"multiLine": false,
					"calculated": false,
					"linkCommand": null,
					"text": null,
					"group": null,
					"placeBeforeProperty": null,
					"placeAfterProperty": null,
					"decorators": [],
					"editorType": null
				},
				{
					"args": [
						32
					],
					"stateType": "default",
					"name": "CuryCreditTotal",
					"bound": true,
					"commitChanges": false,
					"suppressLabel": false,
					"invisible": false,
					"readonly": false,
					"disabled": true,
					"multiLine": false,
					"calculated": false,
					"linkCommand": null,
					"text": null,
					"group": null,
					"placeBeforeProperty": null,
					"placeAfterProperty": null,
					"decorators": [],
					"editorType": null
				},
				{
					"args": null,
					"stateType": "default",
					"name": "CuryControlTotal",
					"bound": true,
					"commitChanges": false,
					"suppressLabel": false,
					"invisible": false,
					"readonly": false,
					"disabled": false,
					"multiLine": false,
					"calculated": false,
					"linkCommand": null,
					"text": null,
					"group": null,
					"placeBeforeProperty": null,
					"placeAfterProperty": null,
					"decorators": [],
					"editorType": null
				}
			],
			"extensions": [],
			"decorators": [],
			"actions": []
		},
		{
			"name": "GLTranModuleBatNbr",
			"dacClassName": null,
			"displayName": null,
			"isCollection": true,
			"featureInstalled": [],
			"fields": [
				{
					"args": null,
					"stateType": "default",
					"name": "RefNbr",
					"bound": true,
					"commitChanges": false,
					"suppressLabel": false,
					"invisible": false,
					"readonly": false,
					"disabled": false,
					"multiLine": false,
					"calculated": false,
					"linkCommand": "ViewDocument",
					"text": null,
					"group": null,
					"placeBeforeProperty": null,
					"placeAfterProperty": null,
					"decorators": [
						{
							"name": {
								"name": "linkCommand"
							},
							"arguments": [
								"ViewDocument"
							]
						}
					],
					"editorType": null
				},
				{
					"args": null,
					"stateType": "default",
					"name": "TranCode",
					"bound": true,
					"commitChanges": false,
					"suppressLabel": false,
					"invisible": false,
					"readonly": false,
					"disabled": false,
					"multiLine": false,
					"calculated": false,
					"linkCommand": null,
					"text": null,
					"group": null,
					"placeBeforeProperty": null,
					"placeAfterProperty": null,
					"decorators": [
						{
							"name": {
								"name": "columnConfig"
							},
							"arguments": [
								{
									"hideViewLink": true
								}
							]
						}
					],
					"editorType": null
				},
				{
					"args": null,
					"stateType": "default",
					"name": "TranDate",
					"bound": true,
					"commitChanges": false,
					"suppressLabel": false,
					"invisible": false,
					"readonly": false,
					"disabled": false,
					"multiLine": false,
					"calculated": false,
					"linkCommand": null,
					"text": null,
					"group": null,
					"placeBeforeProperty": null,
					"placeAfterProperty": null,
					"decorators": [
						{
							"name": {
								"name": "columnConfig"
							},
							"arguments": [
								{
									"allowUpdate": false
								}
							]
						}
					],
					"editorType": null
				},
				{
					"args": null,
					"stateType": "default",
					"name": "BAccountID",
					"bound": true,
					"commitChanges": false,
					"suppressLabel": false,
					"invisible": false,
					"readonly": false,
					"disabled": false,
					"multiLine": false,
					"calculated": false,
					"linkCommand": null,
					"text": null,
					"group": null,
					"placeBeforeProperty": null,
					"placeAfterProperty": null,
					"decorators": [
						{
							"name": {
								"name": "columnConfig"
							},
							"arguments": [
								{
									"allowUpdate": false,
									"hideViewLink": true
								}
							]
						}
					],
					"editorType": null
				},
				{
					"args": null,
					"stateType": "default",
					"name": "LocationID",
					"bound": true,
					"commitChanges": false,
					"suppressLabel": false,
					"invisible": false,
					"readonly": false,
					"disabled": false,
					"multiLine": false,
					"calculated": false,
					"linkCommand": null,
					"text": null,
					"group": null,
					"placeBeforeProperty": null,
					"placeAfterProperty": null,
					"decorators": [
						{
							"name": {
								"name": "columnConfig"
							},
							"arguments": [
								{
									"hideViewLink": true
								}
							]
						}
					],
					"editorType": null
				},
				{
					"args": null,
					"stateType": "default",
					"name": "EntryTypeID",
					"bound": true,
					"commitChanges": false,
					"suppressLabel": false,
					"invisible": false,
					"readonly": false,
					"disabled": false,
					"multiLine": false,
					"calculated": false,
					"linkCommand": null,
					"text": null,
					"group": null,
					"placeBeforeProperty": null,
					"placeAfterProperty": null,
					"decorators": [
						{
							"name": {
								"name": "columnConfig"
							},
							"arguments": [
								{
									"hideViewLink": true
								}
							]
						}
					],
					"editorType": null
				},
				{
					"args": null,
					"stateType": "default",
					"name": "DebitAccountID",
					"bound": true,
					"commitChanges": false,
					"suppressLabel": false,
					"invisible": false,
					"readonly": false,
					"disabled": false,
					"multiLine": false,
					"calculated": false,
					"linkCommand": null,
					"text": null,
					"group": null,
					"placeBeforeProperty": null,
					"placeAfterProperty": null,
					"decorators": [
						{
							"name": {
								"name": "columnConfig"
							},
							"arguments": [
								{
									"hideViewLink": true
								}
							]
						}
					],
					"editorType": null
				},
				{
					"args": null,
					"stateType": "default",
					"name": "DebitSubID",
					"bound": true,
					"commitChanges": false,
					"suppressLabel": false,
					"invisible": false,
					"readonly": false,
					"disabled": false,
					"multiLine": false,
					"calculated": false,
					"linkCommand": null,
					"text": null,
					"group": null,
					"placeBeforeProperty": null,
					"placeAfterProperty": null,
					"decorators": [
						{
							"name": {
								"name": "columnConfig"
							},
							"arguments": [
								{
									"hideViewLink": true
								}
							]
						}
					],
					"editorType": null
				},
				{
					"args": null,
					"stateType": "default",
					"name": "CreditAccountID",
					"bound": true,
					"commitChanges": false,
					"suppressLabel": false,
					"invisible": false,
					"readonly": false,
					"disabled": false,
					"multiLine": false,
					"calculated": false,
					"linkCommand": null,
					"text": null,
					"group": null,
					"placeBeforeProperty": null,
					"placeAfterProperty": null,
					"decorators": [
						{
							"name": {
								"name": "columnConfig"
							},
							"arguments": [
								{
									"hideViewLink": true
								}
							]
						}
					],
					"editorType": null
				},
				{
					"args": null,
					"stateType": "default",
					"name": "CreditSubID",
					"bound": true,
					"commitChanges": false,
					"suppressLabel": false,
					"invisible": false,
					"readonly": false,
					"disabled": false,
					"multiLine": false,
					"calculated": false,
					"linkCommand": null,
					"text": null,
					"group": null,
					"placeBeforeProperty": null,
					"placeAfterProperty": null,
					"decorators": [
						{
							"name": {
								"name": "columnConfig"
							},
							"arguments": [
								{
									"hideViewLink": true
								}
							]
						}
					],
					"editorType": null
				},
				{
					"args": null,
					"stateType": "default",
					"name": "ExtRefNbr",
					"bound": true,
					"commitChanges": false,
					"suppressLabel": false,
					"invisible": false,
					"readonly": false,
					"disabled": false,
					"multiLine": false,
					"calculated": false,
					"linkCommand": null,
					"text": null,
					"group": null,
					"placeBeforeProperty": null,
					"placeAfterProperty": null,
					"decorators": [],
					"editorType": null
				},
				{
					"args": null,
					"stateType": "default",
					"name": "CuryTranTotal",
					"bound": true,
					"commitChanges": false,
					"suppressLabel": false,
					"invisible": false,
					"readonly": false,
					"disabled": false,
					"multiLine": false,
					"calculated": false,
					"linkCommand": null,
					"text": null,
					"group": null,
					"placeBeforeProperty": null,
					"placeAfterProperty": null,
					"decorators": [],
					"editorType": null
				},
				{
					"args": null,
					"stateType": "default",
					"name": "CuryTranAmt",
					"bound": true,
					"commitChanges": false,
					"suppressLabel": false,
					"invisible": false,
					"readonly": false,
					"disabled": false,
					"multiLine": false,
					"calculated": false,
					"linkCommand": null,
					"text": null,
					"group": null,
					"placeBeforeProperty": null,
					"placeAfterProperty": null,
					"decorators": [],
					"editorType": null
				},
				{
					"args": null,
					"stateType": "default",
					"name": "TaxZoneID",
					"bound": true,
					"commitChanges": false,
					"suppressLabel": false,
					"invisible": false,
					"readonly": false,
					"disabled": false,
					"multiLine": false,
					"calculated": false,
					"linkCommand": null,
					"text": null,
					"group": null,
					"placeBeforeProperty": null,
					"placeAfterProperty": null,
					"decorators": [
						{
							"name": {
								"name": "columnConfig"
							},
							"arguments": [
								{
									"hideViewLink": true
								}
							]
						}
					],
					"editorType": null
				},
				{
					"args": null,
					"stateType": "default",
					"name": "TaxCategoryID",
					"bound": true,
					"commitChanges": false,
					"suppressLabel": false,
					"invisible": false,
					"readonly": false,
					"disabled": false,
					"multiLine": false,
					"calculated": false,
					"linkCommand": null,
					"text": null,
					"group": null,
					"placeBeforeProperty": null,
					"placeAfterProperty": null,
					"decorators": [
						{
							"name": {
								"name": "columnConfig"
							},
							"arguments": [
								{
									"hideViewLink": true
								}
							]
						}
					],
					"editorType": null
				},
				{
					"args": null,
					"stateType": "default",
					"name": "CuryTaxAmt",
					"bound": true,
					"commitChanges": false,
					"suppressLabel": false,
					"invisible": false,
					"readonly": false,
					"disabled": false,
					"multiLine": false,
					"calculated": false,
					"linkCommand": "ShowTaxes",
					"text": null,
					"group": null,
					"placeBeforeProperty": null,
					"placeAfterProperty": null,
					"decorators": [
						{
							"name": {
								"name": "linkCommand"
							},
							"arguments": [
								"ShowTaxes"
							]
						}
					],
					"editorType": null
				},
				{
					"args": null,
					"stateType": "default",
					"name": "Split",
					"bound": true,
					"commitChanges": false,
					"suppressLabel": false,
					"invisible": false,
					"readonly": false,
					"disabled": false,
					"multiLine": false,
					"calculated": false,
					"linkCommand": null,
					"text": null,
					"group": null,
					"placeBeforeProperty": null,
					"placeAfterProperty": null,
					"decorators": [
						{
							"name": {
								"name": "columnConfig"
							},
							"arguments": [
								{
									"allowUpdate": false
								}
							]
						}
					],
					"editorType": null
				},
				{
					"args": null,
					"stateType": "default",
					"name": "TranDesc",
					"bound": true,
					"commitChanges": false,
					"suppressLabel": false,
					"invisible": false,
					"readonly": false,
					"disabled": false,
					"multiLine": false,
					"calculated": false,
					"linkCommand": null,
					"text": null,
					"group": null,
					"placeBeforeProperty": null,
					"placeAfterProperty": null,
					"decorators": [],
					"editorType": null
				},
				{
					"args": null,
					"stateType": "default",
					"name": "ProjectID",
					"bound": true,
					"commitChanges": false,
					"suppressLabel": false,
					"invisible": false,
					"readonly": false,
					"disabled": false,
					"multiLine": false,
					"calculated": false,
					"linkCommand": null,
					"text": null,
					"group": null,
					"placeBeforeProperty": null,
					"placeAfterProperty": null,
					"decorators": [
						{
							"name": {
								"name": "columnConfig"
							},
							"arguments": [
								{
									"hideViewLink": true
								}
							]
						}
					],
					"editorType": null
				},
				{
					"args": null,
					"stateType": "default",
					"name": "TaskID",
					"bound": true,
					"commitChanges": false,
					"suppressLabel": false,
					"invisible": false,
					"readonly": false,
					"disabled": false,
					"multiLine": false,
					"calculated": false,
					"linkCommand": null,
					"text": null,
					"group": null,
					"placeBeforeProperty": null,
					"placeAfterProperty": null,
					"decorators": [
						{
							"name": {
								"name": "columnConfig"
							},
							"arguments": [
								{
									"hideViewLink": true
								}
							]
						}
					],
					"editorType": null
				},
				{
					"args": null,
					"stateType": "default",
					"name": "CostCodeID",
					"bound": true,
					"commitChanges": false,
					"suppressLabel": false,
					"invisible": false,
					"readonly": false,
					"disabled": false,
					"multiLine": false,
					"calculated": false,
					"linkCommand": null,
					"text": null,
					"group": null,
					"placeBeforeProperty": null,
					"placeAfterProperty": null,
					"decorators": [
						{
							"name": {
								"name": "columnConfig"
							},
							"arguments": [
								{
									"hideViewLink": true
								}
							]
						}
					],
					"editorType": null
				},
				{
					"args": null,
					"stateType": "default",
					"name": "PaymentMethodID",
					"bound": true,
					"commitChanges": false,
					"suppressLabel": false,
					"invisible": false,
					"readonly": false,
					"disabled": false,
					"multiLine": false,
					"calculated": false,
					"linkCommand": null,
					"text": null,
					"group": null,
					"placeBeforeProperty": null,
					"placeAfterProperty": null,
					"decorators": [
						{
							"name": {
								"name": "columnConfig"
							},
							"arguments": [
								{
									"hideViewLink": true
								}
							]
						}
					],
					"editorType": null
				},
				{
					"args": null,
					"stateType": "default",
					"name": "PMInstanceID",
					"bound": true,
					"commitChanges": false,
					"suppressLabel": false,
					"invisible": false,
					"readonly": false,
					"disabled": false,
					"multiLine": false,
					"calculated": false,
					"linkCommand": null,
					"text": null,
					"group": null,
					"placeBeforeProperty": null,
					"placeAfterProperty": null,
					"decorators": [
						{
							"name": {
								"name": "columnConfig"
							},
							"arguments": [
								{
									"hideViewLink": true
								}
							]
						}
					],
					"editorType": null
				},
				{
					"args": null,
					"stateType": "default",
					"name": "TermsID",
					"bound": true,
					"commitChanges": false,
					"suppressLabel": false,
					"invisible": false,
					"readonly": false,
					"disabled": false,
					"multiLine": false,
					"calculated": false,
					"linkCommand": null,
					"text": null,
					"group": null,
					"placeBeforeProperty": null,
					"placeAfterProperty": null,
					"decorators": [
						{
							"name": {
								"name": "columnConfig"
							},
							"arguments": [
								{
									"hideViewLink": true
								}
							]
						}
					],
					"editorType": null
				},
				{
					"args": null,
					"stateType": "default",
					"name": "DueDate",
					"bound": true,
					"commitChanges": false,
					"suppressLabel": false,
					"invisible": false,
					"readonly": false,
					"disabled": false,
					"multiLine": false,
					"calculated": false,
					"linkCommand": null,
					"text": null,
					"group": null,
					"placeBeforeProperty": null,
					"placeAfterProperty": null,
					"decorators": [],
					"editorType": null
				},
				{
					"args": null,
					"stateType": "default",
					"name": "DiscDate",
					"bound": true,
					"commitChanges": false,
					"suppressLabel": false,
					"invisible": false,
					"readonly": false,
					"disabled": false,
					"multiLine": false,
					"calculated": false,
					"linkCommand": null,
					"text": null,
					"group": null,
					"placeBeforeProperty": null,
					"placeAfterProperty": null,
					"decorators": [],
					"editorType": null
				},
				{
					"args": null,
					"stateType": "default",
					"name": "CuryDiscAmt",
					"bound": true,
					"commitChanges": false,
					"suppressLabel": false,
					"invisible": false,
					"readonly": false,
					"disabled": false,
					"multiLine": false,
					"calculated": false,
					"linkCommand": null,
					"text": null,
					"group": null,
					"placeBeforeProperty": null,
					"placeAfterProperty": null,
					"decorators": [],
					"editorType": null
				},
				{
					"args": [
						2
					],
					"stateType": "default",
					"name": "LineNbr",
					"bound": true,
					"commitChanges": false,
					"suppressLabel": false,
					"invisible": true,
					"readonly": false,
					"disabled": false,
					"multiLine": false,
					"calculated": false,
					"linkCommand": null,
					"text": null,
					"group": null,
					"placeBeforeProperty": null,
					"placeAfterProperty": null,
					"decorators": [
						{
							"name": {
								"name": "columnConfig"
							},
							"arguments": [
								{
									"allowUpdate": false
								}
							]
						}
					],
					"editorType": null
				},
				{
					"args": null,
					"stateType": "default",
					"name": "CuryInclTaxAmt",
					"bound": true,
					"commitChanges": false,
					"suppressLabel": false,
					"invisible": false,
					"readonly": false,
					"disabled": false,
					"multiLine": false,
					"calculated": false,
					"linkCommand": null,
					"text": null,
					"group": null,
					"placeBeforeProperty": null,
					"placeAfterProperty": null,
					"decorators": [],
					"editorType": null
				},
				{
					"args": null,
					"stateType": "default",
					"name": "CuryDocTotal",
					"bound": true,
					"commitChanges": false,
					"suppressLabel": false,
					"invisible": false,
					"readonly": false,
					"disabled": false,
					"multiLine": false,
					"calculated": false,
					"linkCommand": null,
					"text": null,
					"group": null,
					"placeBeforeProperty": null,
					"placeAfterProperty": null,
					"decorators": [],
					"editorType": null
				},
				{
					"args": null,
					"stateType": "default",
					"name": "DocCreated",
					"bound": true,
					"commitChanges": false,
					"suppressLabel": false,
					"invisible": false,
					"readonly": false,
					"disabled": false,
					"multiLine": false,
					"calculated": false,
					"linkCommand": null,
					"text": null,
					"group": null,
					"placeBeforeProperty": null,
					"placeAfterProperty": null,
					"decorators": [],
					"editorType": null
				},
				{
					"args": null,
					"stateType": "default",
					"name": "Released",
					"bound": true,
					"commitChanges": false,
					"suppressLabel": false,
					"invisible": false,
					"readonly": false,
					"disabled": false,
					"multiLine": false,
					"calculated": false,
					"linkCommand": null,
					"text": null,
					"group": null,
					"placeBeforeProperty": null,
					"placeAfterProperty": null,
					"decorators": [],
					"editorType": null
				}
			],
			"extensions": [],
			"decorators": [
				{
					"name": {
						"name": "gridConfig"
					},
					"arguments": [
						{
							"initNewRow": true,
							"syncPosition": true,
							"allowUpdate": false
						}
					]
				}
			],
			"actions": [
				{
					"name": "ViewDocument",
					"decorators": []
				},
				{
					"name": "ShowTaxes",
					"decorators": []
				}
			],
			"allowUpdate": false
		},
		{
			"name": "APPayments",
			"dacClassName": null,
			"displayName": null,
			"isCollection": true,
			"featureInstalled": [],
			"fields": [
				{
					"args": null,
					"stateType": "default",
					"name": "TranCode",
					"bound": true,
					"commitChanges": false,
					"suppressLabel": false,
					"invisible": false,
					"readonly": false,
					"disabled": false,
					"multiLine": false,
					"calculated": false,
					"linkCommand": null,
					"text": null,
					"group": null,
					"placeBeforeProperty": null,
					"placeAfterProperty": null,
					"decorators": [],
					"editorType": null
				},
				{
					"args": null,
					"stateType": "default",
					"name": "RefNbr",
					"bound": true,
					"commitChanges": false,
					"suppressLabel": false,
					"invisible": false,
					"readonly": false,
					"disabled": false,
					"multiLine": false,
					"calculated": false,
					"linkCommand": null,
					"text": null,
					"group": null,
					"placeBeforeProperty": null,
					"placeAfterProperty": null,
					"decorators": [],
					"editorType": null
				},
				{
					"args": null,
					"stateType": "default",
					"name": "TranDate",
					"bound": true,
					"commitChanges": false,
					"suppressLabel": false,
					"invisible": false,
					"readonly": false,
					"disabled": false,
					"multiLine": false,
					"calculated": false,
					"linkCommand": null,
					"text": null,
					"group": null,
					"placeBeforeProperty": null,
					"placeAfterProperty": null,
					"decorators": [],
					"editorType": null
				},
				{
					"args": null,
					"stateType": "default",
					"name": "BAccountID",
					"bound": true,
					"commitChanges": false,
					"suppressLabel": false,
					"invisible": false,
					"readonly": false,
					"disabled": false,
					"multiLine": false,
					"calculated": false,
					"linkCommand": null,
					"text": null,
					"group": null,
					"placeBeforeProperty": null,
					"placeAfterProperty": null,
					"decorators": [],
					"editorType": null
				},
				{
					"args": null,
					"stateType": "default",
					"name": "LocationID",
					"bound": true,
					"commitChanges": false,
					"suppressLabel": false,
					"invisible": false,
					"readonly": false,
					"disabled": false,
					"multiLine": false,
					"calculated": false,
					"linkCommand": null,
					"text": null,
					"group": null,
					"placeBeforeProperty": null,
					"placeAfterProperty": null,
					"decorators": [],
					"editorType": null
				},
				{
					"args": null,
					"stateType": "default",
					"name": "PaymentMethodID",
					"bound": true,
					"commitChanges": false,
					"suppressLabel": false,
					"invisible": false,
					"readonly": false,
					"disabled": false,
					"multiLine": false,
					"calculated": false,
					"linkCommand": null,
					"text": null,
					"group": null,
					"placeBeforeProperty": null,
					"placeAfterProperty": null,
					"decorators": [],
					"editorType": null
				},
				{
					"args": null,
					"stateType": "default",
					"name": "DebitAccountID",
					"bound": true,
					"commitChanges": false,
					"suppressLabel": false,
					"invisible": false,
					"readonly": false,
					"disabled": false,
					"multiLine": false,
					"calculated": false,
					"linkCommand": null,
					"text": null,
					"group": null,
					"placeBeforeProperty": null,
					"placeAfterProperty": null,
					"decorators": [],
					"editorType": null
				},
				{
					"args": null,
					"stateType": "default",
					"name": "DebitSubID",
					"bound": true,
					"commitChanges": false,
					"suppressLabel": false,
					"invisible": false,
					"readonly": false,
					"disabled": false,
					"multiLine": false,
					"calculated": false,
					"linkCommand": null,
					"text": null,
					"group": null,
					"placeBeforeProperty": null,
					"placeAfterProperty": null,
					"decorators": [],
					"editorType": null
				},
				{
					"args": null,
					"stateType": "default",
					"name": "CreditAccountID",
					"bound": true,
					"commitChanges": false,
					"suppressLabel": false,
					"invisible": false,
					"readonly": false,
					"disabled": false,
					"multiLine": false,
					"calculated": false,
					"linkCommand": null,
					"text": null,
					"group": null,
					"placeBeforeProperty": null,
					"placeAfterProperty": null,
					"decorators": [],
					"editorType": null
				},
				{
					"args": null,
					"stateType": "default",
					"name": "CreditSubID",
					"bound": true,
					"commitChanges": false,
					"suppressLabel": false,
					"invisible": false,
					"readonly": false,
					"disabled": false,
					"multiLine": false,
					"calculated": false,
					"linkCommand": null,
					"text": null,
					"group": null,
					"placeBeforeProperty": null,
					"placeAfterProperty": null,
					"decorators": [],
					"editorType": null
				},
				{
					"args": null,
					"stateType": "default",
					"name": "ExtRefNbr",
					"bound": true,
					"commitChanges": false,
					"suppressLabel": false,
					"invisible": false,
					"readonly": false,
					"disabled": false,
					"multiLine": false,
					"calculated": false,
					"linkCommand": null,
					"text": null,
					"group": null,
					"placeBeforeProperty": null,
					"placeAfterProperty": null,
					"decorators": [],
					"editorType": null
				},
				{
					"args": null,
					"stateType": "default",
					"name": "CuryID",
					"bound": true,
					"commitChanges": false,
					"suppressLabel": false,
					"invisible": false,
					"readonly": false,
					"disabled": false,
					"multiLine": false,
					"calculated": false,
					"linkCommand": null,
					"text": null,
					"group": null,
					"placeBeforeProperty": null,
					"placeAfterProperty": null,
					"decorators": [],
					"editorType": null
				},
				{
					"args": null,
					"stateType": "default",
					"name": "CuryApplAmt",
					"bound": true,
					"commitChanges": false,
					"suppressLabel": false,
					"invisible": false,
					"readonly": false,
					"disabled": false,
					"multiLine": false,
					"calculated": false,
					"linkCommand": null,
					"text": null,
					"group": null,
					"placeBeforeProperty": null,
					"placeAfterProperty": null,
					"decorators": [],
					"editorType": null
				},
				{
					"args": null,
					"stateType": "default",
					"name": "curyUnappliedBal",
					"bound": true,
					"commitChanges": false,
					"suppressLabel": false,
					"invisible": false,
					"readonly": false,
					"disabled": false,
					"multiLine": false,
					"calculated": false,
					"linkCommand": null,
					"text": null,
					"group": null,
					"placeBeforeProperty": null,
					"placeAfterProperty": null,
					"decorators": [],
					"editorType": null
				},
				{
					"args": null,
					"stateType": "default",
					"name": "CuryTranAmt",
					"bound": true,
					"commitChanges": false,
					"suppressLabel": false,
					"invisible": false,
					"readonly": false,
					"disabled": false,
					"multiLine": false,
					"calculated": false,
					"linkCommand": null,
					"text": null,
					"group": null,
					"placeBeforeProperty": null,
					"placeAfterProperty": null,
					"decorators": [],
					"editorType": null
				},
				{
					"args": null,
					"stateType": "default",
					"name": "TranDesc",
					"bound": true,
					"commitChanges": false,
					"suppressLabel": false,
					"invisible": false,
					"readonly": false,
					"disabled": false,
					"multiLine": false,
					"calculated": false,
					"linkCommand": null,
					"text": null,
					"group": null,
					"placeBeforeProperty": null,
					"placeAfterProperty": null,
					"decorators": [],
					"editorType": null
				}
			],
			"extensions": [],
			"decorators": [
				{
					"name": {
						"name": "gridConfig"
					},
					"arguments": [
						{
							"syncPosition": true,
							"allowDelete": false,
							"allowInsert": false
						}
					]
				}
			],
			"actions": [],
			"allowDelete": false,
			"allowInsert": false
		},
		{
			"name": "ARPayments",
			"dacClassName": null,
			"displayName": null,
			"isCollection": true,
			"featureInstalled": [],
			"fields": [
				{
					"args": null,
					"stateType": "default",
					"name": "TranCode",
					"bound": true,
					"commitChanges": false,
					"suppressLabel": false,
					"invisible": false,
					"readonly": false,
					"disabled": false,
					"multiLine": false,
					"calculated": false,
					"linkCommand": null,
					"text": null,
					"group": null,
					"placeBeforeProperty": null,
					"placeAfterProperty": null,
					"decorators": [],
					"editorType": null
				},
				{
					"args": null,
					"stateType": "default",
					"name": "RefNbr",
					"bound": true,
					"commitChanges": false,
					"suppressLabel": false,
					"invisible": false,
					"readonly": false,
					"disabled": false,
					"multiLine": false,
					"calculated": false,
					"linkCommand": null,
					"text": null,
					"group": null,
					"placeBeforeProperty": null,
					"placeAfterProperty": null,
					"decorators": [],
					"editorType": null
				},
				{
					"args": null,
					"stateType": "default",
					"name": "TranDate",
					"bound": true,
					"commitChanges": false,
					"suppressLabel": false,
					"invisible": false,
					"readonly": false,
					"disabled": false,
					"multiLine": false,
					"calculated": false,
					"linkCommand": null,
					"text": null,
					"group": null,
					"placeBeforeProperty": null,
					"placeAfterProperty": null,
					"decorators": [],
					"editorType": null
				},
				{
					"args": null,
					"stateType": "default",
					"name": "BAccountID",
					"bound": true,
					"commitChanges": false,
					"suppressLabel": false,
					"invisible": false,
					"readonly": false,
					"disabled": false,
					"multiLine": false,
					"calculated": false,
					"linkCommand": null,
					"text": null,
					"group": null,
					"placeBeforeProperty": null,
					"placeAfterProperty": null,
					"decorators": [],
					"editorType": null
				},
				{
					"args": null,
					"stateType": "default",
					"name": "LocationID",
					"bound": true,
					"commitChanges": false,
					"suppressLabel": false,
					"invisible": false,
					"readonly": false,
					"disabled": false,
					"multiLine": false,
					"calculated": false,
					"linkCommand": null,
					"text": null,
					"group": null,
					"placeBeforeProperty": null,
					"placeAfterProperty": null,
					"decorators": [],
					"editorType": null
				},
				{
					"args": null,
					"stateType": "default",
					"name": "PaymentMethodID",
					"bound": true,
					"commitChanges": false,
					"suppressLabel": false,
					"invisible": false,
					"readonly": false,
					"disabled": false,
					"multiLine": false,
					"calculated": false,
					"linkCommand": null,
					"text": null,
					"group": null,
					"placeBeforeProperty": null,
					"placeAfterProperty": null,
					"decorators": [],
					"editorType": null
				},
				{
					"args": null,
					"stateType": "default",
					"name": "DebitAccountID",
					"bound": true,
					"commitChanges": false,
					"suppressLabel": false,
					"invisible": false,
					"readonly": false,
					"disabled": false,
					"multiLine": false,
					"calculated": false,
					"linkCommand": null,
					"text": null,
					"group": null,
					"placeBeforeProperty": null,
					"placeAfterProperty": null,
					"decorators": [],
					"editorType": null
				},
				{
					"args": null,
					"stateType": "default",
					"name": "DebitSubID",
					"bound": true,
					"commitChanges": false,
					"suppressLabel": false,
					"invisible": false,
					"readonly": false,
					"disabled": false,
					"multiLine": false,
					"calculated": false,
					"linkCommand": null,
					"text": null,
					"group": null,
					"placeBeforeProperty": null,
					"placeAfterProperty": null,
					"decorators": [],
					"editorType": null
				},
				{
					"args": null,
					"stateType": "default",
					"name": "CreditAccountID",
					"bound": true,
					"commitChanges": false,
					"suppressLabel": false,
					"invisible": false,
					"readonly": false,
					"disabled": false,
					"multiLine": false,
					"calculated": false,
					"linkCommand": null,
					"text": null,
					"group": null,
					"placeBeforeProperty": null,
					"placeAfterProperty": null,
					"decorators": [],
					"editorType": null
				},
				{
					"args": null,
					"stateType": "default",
					"name": "CreditSubID",
					"bound": true,
					"commitChanges": false,
					"suppressLabel": false,
					"invisible": false,
					"readonly": false,
					"disabled": false,
					"multiLine": false,
					"calculated": false,
					"linkCommand": null,
					"text": null,
					"group": null,
					"placeBeforeProperty": null,
					"placeAfterProperty": null,
					"decorators": [],
					"editorType": null
				},
				{
					"args": null,
					"stateType": "default",
					"name": "ExtRefNbr",
					"bound": true,
					"commitChanges": false,
					"suppressLabel": false,
					"invisible": false,
					"readonly": false,
					"disabled": false,
					"multiLine": false,
					"calculated": false,
					"linkCommand": null,
					"text": null,
					"group": null,
					"placeBeforeProperty": null,
					"placeAfterProperty": null,
					"decorators": [],
					"editorType": null
				},
				{
					"args": null,
					"stateType": "default",
					"name": "CuryID",
					"bound": true,
					"commitChanges": false,
					"suppressLabel": false,
					"invisible": false,
					"readonly": false,
					"disabled": false,
					"multiLine": false,
					"calculated": false,
					"linkCommand": null,
					"text": null,
					"group": null,
					"placeBeforeProperty": null,
					"placeAfterProperty": null,
					"decorators": [],
					"editorType": null
				},
				{
					"args": null,
					"stateType": "default",
					"name": "CuryApplAmt",
					"bound": true,
					"commitChanges": false,
					"suppressLabel": false,
					"invisible": false,
					"readonly": false,
					"disabled": false,
					"multiLine": false,
					"calculated": false,
					"linkCommand": null,
					"text": null,
					"group": null,
					"placeBeforeProperty": null,
					"placeAfterProperty": null,
					"decorators": [],
					"editorType": null
				},
				{
					"args": null,
					"stateType": "default",
					"name": "curyUnappliedBal",
					"bound": true,
					"commitChanges": false,
					"suppressLabel": false,
					"invisible": false,
					"readonly": false,
					"disabled": false,
					"multiLine": false,
					"calculated": false,
					"linkCommand": null,
					"text": null,
					"group": null,
					"placeBeforeProperty": null,
					"placeAfterProperty": null,
					"decorators": [],
					"editorType": null
				},
				{
					"args": null,
					"stateType": "default",
					"name": "CuryTranAmt",
					"bound": true,
					"commitChanges": false,
					"suppressLabel": false,
					"invisible": false,
					"readonly": false,
					"disabled": false,
					"multiLine": false,
					"calculated": false,
					"linkCommand": null,
					"text": null,
					"group": null,
					"placeBeforeProperty": null,
					"placeAfterProperty": null,
					"decorators": [],
					"editorType": null
				},
				{
					"args": null,
					"stateType": "default",
					"name": "TranDesc",
					"bound": true,
					"commitChanges": false,
					"suppressLabel": false,
					"invisible": false,
					"readonly": false,
					"disabled": false,
					"multiLine": false,
					"calculated": false,
					"linkCommand": null,
					"text": null,
					"group": null,
					"placeBeforeProperty": null,
					"placeAfterProperty": null,
					"decorators": [],
					"editorType": null
				}
			],
			"extensions": [],
			"decorators": [
				{
					"name": {
						"name": "gridConfig"
					},
					"arguments": [
						{
							"syncPosition": true,
							"allowDelete": false,
							"allowInsert": false
						}
					]
				}
			],
			"actions": [],
			"allowDelete": false,
			"allowInsert": false
		},
		{
			"name": "APAdjustments",
			"dacClassName": null,
			"displayName": null,
			"isCollection": true,
			"featureInstalled": [],
			"fields": [
				{
					"args": null,
					"stateType": "default",
					"name": "AdjdDocType",
					"bound": true,
					"commitChanges": false,
					"suppressLabel": false,
					"invisible": false,
					"readonly": false,
					"disabled": false,
					"multiLine": false,
					"calculated": false,
					"linkCommand": null,
					"text": null,
					"group": null,
					"placeBeforeProperty": null,
					"placeAfterProperty": null,
					"decorators": [],
					"editorType": null
				},
				{
					"args": null,
					"stateType": "default",
					"name": "AdjdRefNbr",
					"bound": true,
					"commitChanges": false,
					"suppressLabel": false,
					"invisible": false,
					"readonly": false,
					"disabled": false,
					"multiLine": false,
					"calculated": false,
					"linkCommand": null,
					"text": null,
					"group": null,
					"placeBeforeProperty": null,
					"placeAfterProperty": null,
					"decorators": [],
					"editorType": null
				},
				{
					"args": null,
					"stateType": "default",
					"name": "CuryAdjgAmt",
					"bound": true,
					"commitChanges": false,
					"suppressLabel": false,
					"invisible": false,
					"readonly": false,
					"disabled": false,
					"multiLine": false,
					"calculated": false,
					"linkCommand": null,
					"text": null,
					"group": null,
					"placeBeforeProperty": null,
					"placeAfterProperty": null,
					"decorators": [],
					"editorType": null
				},
				{
					"args": null,
					"stateType": "default",
					"name": "CuryAdjgDiscAmt",
					"bound": true,
					"commitChanges": false,
					"suppressLabel": false,
					"invisible": false,
					"readonly": false,
					"disabled": false,
					"multiLine": false,
					"calculated": false,
					"linkCommand": null,
					"text": null,
					"group": null,
					"placeBeforeProperty": null,
					"placeAfterProperty": null,
					"decorators": [],
					"editorType": null
				},
				{
					"args": null,
					"stateType": "default",
					"name": "CuryAdjgWhTaxAmt",
					"bound": true,
					"commitChanges": false,
					"suppressLabel": false,
					"invisible": false,
					"readonly": false,
					"disabled": false,
					"multiLine": false,
					"calculated": false,
					"linkCommand": null,
					"text": null,
					"group": null,
					"placeBeforeProperty": null,
					"placeAfterProperty": null,
					"decorators": [],
					"editorType": null
				},
				{
					"args": null,
					"stateType": "default",
					"name": "AdjdDocDate",
					"bound": true,
					"commitChanges": false,
					"suppressLabel": false,
					"invisible": false,
					"readonly": false,
					"disabled": false,
					"multiLine": false,
					"calculated": false,
					"linkCommand": null,
					"text": null,
					"group": null,
					"placeBeforeProperty": null,
					"placeAfterProperty": null,
					"decorators": [],
					"editorType": null
				},
				{
					"args": null,
					"stateType": "default",
					"name": "APInvoice__DueDate",
					"bound": true,
					"commitChanges": false,
					"suppressLabel": false,
					"invisible": false,
					"readonly": false,
					"disabled": false,
					"multiLine": false,
					"calculated": false,
					"linkCommand": null,
					"text": null,
					"group": null,
					"placeBeforeProperty": null,
					"placeAfterProperty": null,
					"decorators": [],
					"editorType": null
				},
				{
					"args": null,
					"stateType": "default",
					"name": "APInvoice__DiscDate",
					"bound": true,
					"commitChanges": false,
					"suppressLabel": false,
					"invisible": false,
					"readonly": false,
					"disabled": false,
					"multiLine": false,
					"calculated": false,
					"linkCommand": null,
					"text": null,
					"group": null,
					"placeBeforeProperty": null,
					"placeAfterProperty": null,
					"decorators": [],
					"editorType": null
				},
				{
					"args": null,
					"stateType": "default",
					"name": "CuryDocBal",
					"bound": true,
					"commitChanges": false,
					"suppressLabel": false,
					"invisible": false,
					"readonly": false,
					"disabled": false,
					"multiLine": false,
					"calculated": false,
					"linkCommand": null,
					"text": null,
					"group": null,
					"placeBeforeProperty": null,
					"placeAfterProperty": null,
					"decorators": [],
					"editorType": null
				},
				{
					"args": null,
					"stateType": "default",
					"name": "CuryDiscBal",
					"bound": true,
					"commitChanges": false,
					"suppressLabel": false,
					"invisible": false,
					"readonly": false,
					"disabled": false,
					"multiLine": false,
					"calculated": false,
					"linkCommand": null,
					"text": null,
					"group": null,
					"placeBeforeProperty": null,
					"placeAfterProperty": null,
					"decorators": [],
					"editorType": null
				},
				{
					"args": null,
					"stateType": "default",
					"name": "CuryWhTaxBal",
					"bound": true,
					"commitChanges": false,
					"suppressLabel": false,
					"invisible": false,
					"readonly": false,
					"disabled": false,
					"multiLine": false,
					"calculated": false,
					"linkCommand": null,
					"text": null,
					"group": null,
					"placeBeforeProperty": null,
					"placeAfterProperty": null,
					"decorators": [],
					"editorType": null
				},
				{
					"args": null,
					"stateType": "default",
					"name": "APInvoice__DocDesc",
					"bound": true,
					"commitChanges": false,
					"suppressLabel": false,
					"invisible": false,
					"readonly": false,
					"disabled": false,
					"multiLine": false,
					"calculated": false,
					"linkCommand": null,
					"text": null,
					"group": null,
					"placeBeforeProperty": null,
					"placeAfterProperty": null,
					"decorators": [],
					"editorType": null
				},
				{
					"args": null,
					"stateType": "default",
					"name": "AdjdCuryID",
					"bound": true,
					"commitChanges": false,
					"suppressLabel": false,
					"invisible": false,
					"readonly": false,
					"disabled": false,
					"multiLine": false,
					"calculated": false,
					"linkCommand": null,
					"text": null,
					"group": null,
					"placeBeforeProperty": null,
					"placeAfterProperty": null,
					"decorators": [],
					"editorType": null
				},
				{
					"args": null,
					"stateType": "default",
					"name": "AdjdFinPeriodID",
					"bound": true,
					"commitChanges": false,
					"suppressLabel": false,
					"invisible": false,
					"readonly": false,
					"disabled": false,
					"multiLine": false,
					"calculated": false,
					"linkCommand": null,
					"text": null,
					"group": null,
					"placeBeforeProperty": null,
					"placeAfterProperty": null,
					"decorators": [],
					"editorType": null
				},
				{
					"args": null,
					"stateType": "default",
					"name": "APInvoice__InvoiceNbr",
					"bound": true,
					"commitChanges": false,
					"suppressLabel": false,
					"invisible": false,
					"readonly": false,
					"disabled": false,
					"multiLine": false,
					"calculated": false,
					"linkCommand": null,
					"text": null,
					"group": null,
					"placeBeforeProperty": null,
					"placeAfterProperty": null,
					"decorators": [],
					"editorType": null
				},
				{
					"args": null,
					"stateType": "default",
					"name": "VendorID",
					"bound": true,
					"commitChanges": false,
					"suppressLabel": false,
					"invisible": false,
					"readonly": false,
					"disabled": false,
					"multiLine": false,
					"calculated": false,
					"linkCommand": null,
					"text": null,
					"group": null,
					"placeBeforeProperty": null,
					"placeAfterProperty": null,
					"decorators": [],
					"editorType": null
				}
			],
			"extensions": [],
			"decorators": [],
			"actions": []
		},
		{
			"name": "ARAdjustments",
			"dacClassName": null,
			"displayName": null,
			"isCollection": true,
			"featureInstalled": [],
			"fields": [
				{
					"args": null,
					"stateType": "default",
					"name": "AdjdDocType",
					"bound": true,
					"commitChanges": false,
					"suppressLabel": false,
					"invisible": false,
					"readonly": false,
					"disabled": false,
					"multiLine": false,
					"calculated": false,
					"linkCommand": null,
					"text": null,
					"group": null,
					"placeBeforeProperty": null,
					"placeAfterProperty": null,
					"decorators": [],
					"editorType": null
				},
				{
					"args": null,
					"stateType": "default",
					"name": "AdjdRefNbr",
					"bound": true,
					"commitChanges": false,
					"suppressLabel": false,
					"invisible": false,
					"readonly": false,
					"disabled": false,
					"multiLine": false,
					"calculated": false,
					"linkCommand": null,
					"text": null,
					"group": null,
					"placeBeforeProperty": null,
					"placeAfterProperty": null,
					"decorators": [],
					"editorType": null
				},
				{
					"args": null,
					"stateType": "default",
					"name": "CuryAdjgAmt",
					"bound": true,
					"commitChanges": false,
					"suppressLabel": false,
					"invisible": false,
					"readonly": false,
					"disabled": false,
					"multiLine": false,
					"calculated": false,
					"linkCommand": null,
					"text": null,
					"group": null,
					"placeBeforeProperty": null,
					"placeAfterProperty": null,
					"decorators": [],
					"editorType": null
				},
				{
					"args": null,
					"stateType": "default",
					"name": "CuryAdjgDiscAmt",
					"bound": true,
					"commitChanges": false,
					"suppressLabel": false,
					"invisible": false,
					"readonly": false,
					"disabled": false,
					"multiLine": false,
					"calculated": false,
					"linkCommand": null,
					"text": null,
					"group": null,
					"placeBeforeProperty": null,
					"placeAfterProperty": null,
					"decorators": [],
					"editorType": null
				},
				{
					"args": null,
					"stateType": "default",
					"name": "CuryAdjgWOAmt",
					"bound": true,
					"commitChanges": false,
					"suppressLabel": false,
					"invisible": false,
					"readonly": false,
					"disabled": false,
					"multiLine": false,
					"calculated": false,
					"linkCommand": null,
					"text": null,
					"group": null,
					"placeBeforeProperty": null,
					"placeAfterProperty": null,
					"decorators": [],
					"editorType": null
				},
				{
					"args": null,
					"stateType": "default",
					"name": "WriteOffReasonCode",
					"bound": true,
					"commitChanges": false,
					"suppressLabel": false,
					"invisible": false,
					"readonly": false,
					"disabled": false,
					"multiLine": false,
					"calculated": false,
					"linkCommand": null,
					"text": null,
					"group": null,
					"placeBeforeProperty": null,
					"placeAfterProperty": null,
					"decorators": [],
					"editorType": null
				},
				{
					"args": null,
					"stateType": "default",
					"name": "AdjdDocDate",
					"bound": true,
					"commitChanges": false,
					"suppressLabel": false,
					"invisible": false,
					"readonly": false,
					"disabled": false,
					"multiLine": false,
					"calculated": false,
					"linkCommand": null,
					"text": null,
					"group": null,
					"placeBeforeProperty": null,
					"placeAfterProperty": null,
					"decorators": [
						{
							"name": {
								"name": "columnConfig"
							},
							"arguments": [
								{
									"allowUpdate": false
								}
							]
						}
					],
					"editorType": null
				},
				{
					"args": null,
					"stateType": "default",
					"name": "ARInvoice__DueDate",
					"bound": true,
					"commitChanges": false,
					"suppressLabel": false,
					"invisible": false,
					"readonly": false,
					"disabled": false,
					"multiLine": false,
					"calculated": false,
					"linkCommand": null,
					"text": null,
					"group": null,
					"placeBeforeProperty": null,
					"placeAfterProperty": null,
					"decorators": [],
					"editorType": null
				},
				{
					"args": null,
					"stateType": "default",
					"name": "ARInvoice__DiscDate",
					"bound": true,
					"commitChanges": false,
					"suppressLabel": false,
					"invisible": false,
					"readonly": false,
					"disabled": false,
					"multiLine": false,
					"calculated": false,
					"linkCommand": null,
					"text": null,
					"group": null,
					"placeBeforeProperty": null,
					"placeAfterProperty": null,
					"decorators": [],
					"editorType": null
				},
				{
					"args": null,
					"stateType": "default",
					"name": "CuryDocBal",
					"bound": true,
					"commitChanges": false,
					"suppressLabel": false,
					"invisible": false,
					"readonly": false,
					"disabled": false,
					"multiLine": false,
					"calculated": false,
					"linkCommand": null,
					"text": null,
					"group": null,
					"placeBeforeProperty": null,
					"placeAfterProperty": null,
					"decorators": [],
					"editorType": null
				},
				{
					"args": null,
					"stateType": "default",
					"name": "CuryDiscBal",
					"bound": true,
					"commitChanges": false,
					"suppressLabel": false,
					"invisible": false,
					"readonly": false,
					"disabled": false,
					"multiLine": false,
					"calculated": false,
					"linkCommand": null,
					"text": null,
					"group": null,
					"placeBeforeProperty": null,
					"placeAfterProperty": null,
					"decorators": [],
					"editorType": null
				},
				{
					"args": null,
					"stateType": "default",
					"name": "CuryWOBal",
					"bound": true,
					"commitChanges": false,
					"suppressLabel": false,
					"invisible": false,
					"readonly": false,
					"disabled": false,
					"multiLine": false,
					"calculated": false,
					"linkCommand": null,
					"text": null,
					"group": null,
					"placeBeforeProperty": null,
					"placeAfterProperty": null,
					"decorators": [],
					"editorType": null
				},
				{
					"args": null,
					"stateType": "default",
					"name": "ARInvoice__DocDesc",
					"bound": true,
					"commitChanges": false,
					"suppressLabel": false,
					"invisible": false,
					"readonly": false,
					"disabled": false,
					"multiLine": false,
					"calculated": false,
					"linkCommand": null,
					"text": null,
					"group": null,
					"placeBeforeProperty": null,
					"placeAfterProperty": null,
					"decorators": [],
					"editorType": null
				},
				{
					"args": null,
					"stateType": "default",
					"name": "AdjdCuryID",
					"bound": true,
					"commitChanges": false,
					"suppressLabel": false,
					"invisible": false,
					"readonly": false,
					"disabled": false,
					"multiLine": false,
					"calculated": false,
					"linkCommand": null,
					"text": null,
					"group": null,
					"placeBeforeProperty": null,
					"placeAfterProperty": null,
					"decorators": [],
					"editorType": null
				},
				{
					"args": null,
					"stateType": "default",
					"name": "AdjdFinPeriodID",
					"bound": true,
					"commitChanges": false,
					"suppressLabel": false,
					"invisible": false,
					"readonly": false,
					"disabled": false,
					"multiLine": false,
					"calculated": false,
					"linkCommand": null,
					"text": null,
					"group": null,
					"placeBeforeProperty": null,
					"placeAfterProperty": null,
					"decorators": [],
					"editorType": null
				},
				{
					"args": null,
					"stateType": "default",
					"name": "ARInvoice__InvoiceNbr",
					"bound": true,
					"commitChanges": false,
					"suppressLabel": false,
					"invisible": false,
					"readonly": false,
					"disabled": false,
					"multiLine": false,
					"calculated": false,
					"linkCommand": null,
					"text": null,
					"group": null,
					"placeBeforeProperty": null,
					"placeAfterProperty": null,
					"decorators": [],
					"editorType": null
				},
				{
					"args": null,
					"stateType": "default",
					"name": "CustomerID",
					"bound": true,
					"commitChanges": false,
					"suppressLabel": false,
					"invisible": false,
					"readonly": false,
					"disabled": false,
					"multiLine": false,
					"calculated": false,
					"linkCommand": null,
					"text": null,
					"group": null,
					"placeBeforeProperty": null,
					"placeAfterProperty": null,
					"decorators": [],
					"editorType": null
				}
			],
			"extensions": [],
			"decorators": [],
			"actions": []
		},
		{
			"name": "GLTransactions",
			"dacClassName": null,
			"displayName": null,
			"isCollection": true,
			"featureInstalled": [],
			"fields": [
				{
					"args": null,
					"stateType": "default",
					"name": "RefNbr",
					"bound": true,
					"commitChanges": false,
					"suppressLabel": false,
					"invisible": false,
					"readonly": false,
					"disabled": false,
					"multiLine": false,
					"calculated": false,
					"linkCommand": null,
					"text": null,
					"group": null,
					"placeBeforeProperty": null,
					"placeAfterProperty": null,
					"decorators": [],
					"editorType": null
				},
				{
					"args": null,
					"stateType": "default",
					"name": "Module",
					"bound": true,
					"commitChanges": false,
					"suppressLabel": false,
					"invisible": false,
					"readonly": false,
					"disabled": false,
					"multiLine": false,
					"calculated": false,
					"linkCommand": null,
					"text": null,
					"group": null,
					"placeBeforeProperty": null,
					"placeAfterProperty": null,
					"decorators": [],
					"editorType": null
				},
				{
					"args": null,
					"stateType": "default",
					"name": "BatchNbr",
					"bound": true,
					"commitChanges": false,
					"suppressLabel": false,
					"invisible": false,
					"readonly": false,
					"disabled": false,
					"multiLine": false,
					"calculated": false,
					"linkCommand": null,
					"text": null,
					"group": null,
					"placeBeforeProperty": null,
					"placeAfterProperty": null,
					"decorators": [
						{
							"name": {
								"name": "columnConfig"
							},
							"arguments": [
								{
									"hideViewLink": true
								}
							]
						}
					],
					"editorType": null
				},
				{
					"args": null,
					"stateType": "default",
					"name": "TranDate",
					"bound": true,
					"commitChanges": false,
					"suppressLabel": false,
					"invisible": false,
					"readonly": false,
					"disabled": false,
					"multiLine": false,
					"calculated": false,
					"linkCommand": null,
					"text": null,
					"group": null,
					"placeBeforeProperty": null,
					"placeAfterProperty": null,
					"decorators": [],
					"editorType": null
				},
				{
					"args": null,
					"stateType": "default",
					"name": "AccountID",
					"bound": true,
					"commitChanges": false,
					"suppressLabel": false,
					"invisible": false,
					"readonly": false,
					"disabled": false,
					"multiLine": false,
					"calculated": false,
					"linkCommand": null,
					"text": null,
					"group": null,
					"placeBeforeProperty": null,
					"placeAfterProperty": null,
					"decorators": [
						{
							"name": {
								"name": "columnConfig"
							},
							"arguments": [
								{
									"hideViewLink": true
								}
							]
						}
					],
					"editorType": null
				},
				{
					"args": null,
					"stateType": "default",
					"name": "SubID",
					"bound": true,
					"commitChanges": false,
					"suppressLabel": false,
					"invisible": false,
					"readonly": false,
					"disabled": false,
					"multiLine": false,
					"calculated": false,
					"linkCommand": null,
					"text": null,
					"group": null,
					"placeBeforeProperty": null,
					"placeAfterProperty": null,
					"decorators": [
						{
							"name": {
								"name": "columnConfig"
							},
							"arguments": [
								{
									"hideViewLink": true
								}
							]
						}
					],
					"editorType": null
				},
				{
					"args": null,
					"stateType": "default",
					"name": "Qty",
					"bound": true,
					"commitChanges": false,
					"suppressLabel": false,
					"invisible": false,
					"readonly": false,
					"disabled": false,
					"multiLine": false,
					"calculated": false,
					"linkCommand": null,
					"text": null,
					"group": null,
					"placeBeforeProperty": null,
					"placeAfterProperty": null,
					"decorators": [],
					"editorType": null
				},
				{
					"args": null,
					"stateType": "default",
					"name": "CuryID",
					"bound": true,
					"commitChanges": false,
					"suppressLabel": false,
					"invisible": false,
					"readonly": false,
					"disabled": false,
					"multiLine": false,
					"calculated": false,
					"linkCommand": null,
					"text": null,
					"group": null,
					"placeBeforeProperty": null,
					"placeAfterProperty": null,
					"decorators": [],
					"editorType": null
				},
				{
					"args": null,
					"stateType": "default",
					"name": "CuryDebitAmt",
					"bound": true,
					"commitChanges": false,
					"suppressLabel": false,
					"invisible": false,
					"readonly": false,
					"disabled": false,
					"multiLine": false,
					"calculated": false,
					"linkCommand": null,
					"text": null,
					"group": null,
					"placeBeforeProperty": null,
					"placeAfterProperty": null,
					"decorators": [],
					"editorType": null
				},
				{
					"args": null,
					"stateType": "default",
					"name": "CuryCreditAmt",
					"bound": true,
					"commitChanges": false,
					"suppressLabel": false,
					"invisible": false,
					"readonly": false,
					"disabled": false,
					"multiLine": false,
					"calculated": false,
					"linkCommand": null,
					"text": null,
					"group": null,
					"placeBeforeProperty": null,
					"placeAfterProperty": null,
					"decorators": [],
					"editorType": null
				},
				{
					"args": null,
					"stateType": "default",
					"name": "TranDesc",
					"bound": true,
					"commitChanges": false,
					"suppressLabel": false,
					"invisible": false,
					"readonly": false,
					"disabled": false,
					"multiLine": false,
					"calculated": false,
					"linkCommand": null,
					"text": null,
					"group": null,
					"placeBeforeProperty": null,
					"placeAfterProperty": null,
					"decorators": [],
					"editorType": null
				}
			],
			"extensions": [],
			"decorators": [],
			"actions": []
		},
		{
			"name": "CurrentDocTaxes",
			"dacClassName": null,
			"displayName": null,
			"isCollection": true,
			"featureInstalled": [],
			"fields": [
				{
					"args": null,
					"stateType": "default",
					"name": "TaxID",
					"bound": true,
					"commitChanges": false,
					"suppressLabel": false,
					"invisible": false,
					"readonly": false,
					"disabled": false,
					"multiLine": false,
					"calculated": false,
					"linkCommand": null,
					"text": null,
					"group": null,
					"placeBeforeProperty": null,
					"placeAfterProperty": null,
					"decorators": [],
					"editorType": null
				},
				{
					"args": null,
					"stateType": "default",
					"name": "CuryTaxableAmt",
					"bound": true,
					"commitChanges": false,
					"suppressLabel": false,
					"invisible": false,
					"readonly": false,
					"disabled": false,
					"multiLine": false,
					"calculated": false,
					"linkCommand": null,
					"text": null,
					"group": null,
					"placeBeforeProperty": null,
					"placeAfterProperty": null,
					"decorators": [],
					"editorType": null
				},
				{
					"args": null,
					"stateType": "default",
					"name": "TaxRate",
					"bound": true,
					"commitChanges": false,
					"suppressLabel": false,
					"invisible": false,
					"readonly": false,
					"disabled": false,
					"multiLine": false,
					"calculated": false,
					"linkCommand": null,
					"text": null,
					"group": null,
					"placeBeforeProperty": null,
					"placeAfterProperty": null,
					"decorators": [],
					"editorType": null
				},
				{
					"args": null,
					"stateType": "default",
					"name": "CuryTaxAmt",
					"bound": true,
					"commitChanges": false,
					"suppressLabel": false,
					"invisible": false,
					"readonly": false,
					"disabled": false,
					"multiLine": false,
					"calculated": false,
					"linkCommand": null,
					"text": null,
					"group": null,
					"placeBeforeProperty": null,
					"placeAfterProperty": null,
					"decorators": [],
					"editorType": null
				},
				{
					"args": null,
					"stateType": "default",
					"name": "NonDeductibleTaxRate",
					"bound": true,
					"commitChanges": false,
					"suppressLabel": false,
					"invisible": false,
					"readonly": false,
					"disabled": false,
					"multiLine": false,
					"calculated": false,
					"linkCommand": null,
					"text": null,
					"group": null,
					"placeBeforeProperty": null,
					"placeAfterProperty": null,
					"decorators": [],
					"editorType": null
				},
				{
					"args": null,
					"stateType": "default",
					"name": "CuryExpenseAmt",
					"bound": true,
					"commitChanges": false,
					"suppressLabel": false,
					"invisible": false,
					"readonly": false,
					"disabled": false,
					"multiLine": false,
					"calculated": false,
					"linkCommand": null,
					"text": null,
					"group": null,
					"placeBeforeProperty": null,
					"placeAfterProperty": null,
					"decorators": [],
					"editorType": null
				}
			],
			"extensions": [],
			"decorators": [
				{
					"name": {
						"name": "gridConfig"
					},
					"arguments": [
						{
							"syncPosition": true,
							"initNewRow": true
						}
					]
				}
			],
			"actions": []
		},
		{
			"name": "_GLDocBatch_CurrencyInfo_",
			"dacClassName": null,
			"displayName": null,
			"isCollection": false,
			"featureInstalled": [],
			"fields": [
				{
					"args": null,
					"stateType": "default",
					"name": "CuryInfoID",
					"bound": true,
					"commitChanges": false,
					"suppressLabel": false,
					"invisible": false,
					"readonly": false,
					"disabled": false,
					"multiLine": false,
					"calculated": false,
					"linkCommand": null,
					"text": null,
					"group": null,
					"placeBeforeProperty": null,
					"placeAfterProperty": null,
					"decorators": [],
					"editorType": null
				},
				{
					"args": null,
					"stateType": "default",
					"name": "BaseCuryID",
					"bound": true,
					"commitChanges": false,
					"suppressLabel": false,
					"invisible": false,
					"readonly": false,
					"disabled": false,
					"multiLine": false,
					"calculated": false,
					"linkCommand": null,
					"text": null,
					"group": null,
					"placeBeforeProperty": null,
					"placeAfterProperty": null,
					"decorators": [],
					"editorType": null
				},
				{
					"args": null,
					"stateType": "default",
					"name": "BaseCalc",
					"bound": true,
					"commitChanges": false,
					"suppressLabel": false,
					"invisible": false,
					"readonly": false,
					"disabled": false,
					"multiLine": false,
					"calculated": false,
					"linkCommand": null,
					"text": null,
					"group": null,
					"placeBeforeProperty": null,
					"placeAfterProperty": null,
					"decorators": [],
					"editorType": null
				},
				{
					"args": [
						16
					],
					"stateType": "default",
					"name": "CuryID",
					"bound": true,
					"commitChanges": true,
					"suppressLabel": false,
					"invisible": false,
					"readonly": false,
					"disabled": false,
					"multiLine": false,
					"calculated": false,
					"linkCommand": null,
					"text": null,
					"group": null,
					"placeBeforeProperty": null,
					"placeAfterProperty": null,
					"decorators": [],
					"editorType": null
				},
				{
					"args": null,
					"stateType": "default",
					"name": "DisplayCuryID",
					"bound": true,
					"commitChanges": false,
					"suppressLabel": false,
					"invisible": false,
					"readonly": false,
					"disabled": false,
					"multiLine": false,
					"calculated": false,
					"linkCommand": null,
					"text": null,
					"group": null,
					"placeBeforeProperty": null,
					"placeAfterProperty": null,
					"decorators": [],
					"editorType": null
				},
				{
					"args": [
						16
					],
					"stateType": "default",
					"name": "CuryRateTypeID",
					"bound": true,
					"commitChanges": true,
					"suppressLabel": false,
					"invisible": false,
					"readonly": false,
					"disabled": false,
					"multiLine": false,
					"calculated": false,
					"linkCommand": null,
					"text": null,
					"group": null,
					"placeBeforeProperty": null,
					"placeAfterProperty": null,
					"decorators": [],
					"editorType": null
				},
				{
					"args": null,
					"stateType": "default",
					"name": "BasePrecision",
					"bound": true,
					"commitChanges": false,
					"suppressLabel": false,
					"invisible": false,
					"readonly": false,
					"disabled": false,
					"multiLine": false,
					"calculated": false,
					"linkCommand": null,
					"text": null,
					"group": null,
					"placeBeforeProperty": null,
					"placeAfterProperty": null,
					"decorators": [],
					"editorType": null
				},
				{
					"args": [
						16
					],
					"stateType": "default",
					"name": "CuryRate",
					"bound": true,
					"commitChanges": true,
					"suppressLabel": false,
					"invisible": false,
					"readonly": false,
					"disabled": false,
					"multiLine": false,
					"calculated": false,
					"linkCommand": null,
					"text": null,
					"group": null,
					"placeBeforeProperty": null,
					"placeAfterProperty": null,
					"decorators": [],
					"editorType": null
				},
				{
					"args": [
						16
					],
					"stateType": "default",
					"name": "CuryEffDate",
					"bound": true,
					"commitChanges": true,
					"suppressLabel": false,
					"invisible": false,
					"readonly": false,
					"disabled": false,
					"multiLine": false,
					"calculated": false,
					"linkCommand": null,
					"text": null,
					"group": null,
					"placeBeforeProperty": null,
					"placeAfterProperty": null,
					"decorators": [],
					"editorType": null
				},
				{
					"args": [
						16
					],
					"stateType": "default",
					"name": "RecipRate",
					"bound": true,
					"commitChanges": true,
					"suppressLabel": false,
					"invisible": false,
					"readonly": false,
					"disabled": false,
					"multiLine": false,
					"calculated": false,
					"linkCommand": null,
					"text": null,
					"group": null,
					"placeBeforeProperty": null,
					"placeAfterProperty": null,
					"decorators": [],
					"editorType": null
				},
				{
					"args": [
						16
					],
					"stateType": "default",
					"name": "SampleCuryRate",
					"bound": true,
					"commitChanges": true,
					"suppressLabel": false,
					"invisible": false,
					"readonly": false,
					"disabled": false,
					"multiLine": false,
					"calculated": false,
					"linkCommand": null,
					"text": null,
					"group": null,
					"placeBeforeProperty": null,
					"placeAfterProperty": null,
					"decorators": [],
					"editorType": null
				},
				{
					"args": [
						16
					],
					"stateType": "default",
					"name": "SampleRecipRate",
					"bound": true,
					"commitChanges": true,
					"suppressLabel": false,
					"invisible": false,
					"readonly": false,
					"disabled": false,
					"multiLine": false,
					"calculated": false,
					"linkCommand": null,
					"text": null,
					"group": null,
					"placeBeforeProperty": null,
					"placeAfterProperty": null,
					"decorators": [],
					"editorType": null
				}
			],
			"extensions": [],
			"decorators": [],
			"actions": []
		}
	],
	"extensions": [],
	"decorators": [
		{
			"name": {
				"name": "graphInfo"
			},
			"arguments": [
				{
					"graphType": "PX.Objects.GL.JournalWithSubEntry",
					"primaryView": "BatchModule",
					"showUDFIndicator": true
				}
			]
		}
	]
}