{
	"name": "SM202005",
	"graphName": "PX.SM.WikiSetupMaint",
	"primaryView": "Wikis",
	"featureInstalled": [],
	"actions": [
		{
			"name": "importToDITA",
			"decorators": []
		}
	],
	"views": [
		{
			"name": "ClearingFilter",
			"dacClassName": null,
			"displayName": "Choose date",
			"isCollection": false,
			"featureInstalled": [],
			"fields": [
				{
					"args": [
						16
					],
					"stateType": "default",
					"name": "Till",
					"bound": true,
					"commitChanges": true,
					"suppressLabel": false,
					"invisible": false,
					"readonly": false,
					"disabled": false,
					"multiLine": false,
					"calculated": false,
					"linkCommand": null,
					"text": null,
					"group": null,
					"placeBeforeProperty": null,
					"placeAfterProperty": null,
					"decorators": [],
					"editorType": null
				}
			],
			"extensions": [],
			"decorators": [
				{
					"name": {
						"name": "viewInfo"
					},
					"arguments": [
						{
							"containerName": "Choose date"
						}
					]
				}
			],
			"actions": []
		},
		{
			"name": "Wikis",
			"dacClassName": null,
			"displayName": "Wiki",
			"isCollection": false,
			"featureInstalled": [],
			"fields": [
				{
					"args": null,
					"stateType": "default",
					"name": "Name",
					"bound": true,
					"commitChanges": false,
					"suppressLabel": false,
					"invisible": false,
					"readonly": false,
					"disabled": false,
					"multiLine": false,
					"calculated": false,
					"linkCommand": null,
					"text": null,
					"group": null,
					"placeBeforeProperty": null,
					"placeAfterProperty": null,
					"decorators": [],
					"editorType": null
				},
				{
					"args": null,
					"stateType": "default",
					"name": "WikiTitle",
					"bound": true,
					"commitChanges": false,
					"suppressLabel": false,
					"invisible": false,
					"readonly": false,
					"disabled": false,
					"multiLine": false,
					"calculated": false,
					"linkCommand": null,
					"text": null,
					"group": null,
					"placeBeforeProperty": null,
					"placeAfterProperty": null,
					"decorators": [],
					"editorType": null
				},
				{
					"args": [
						32
					],
					"stateType": "default",
					"name": "CreatedByID",
					"bound": true,
					"commitChanges": false,
					"suppressLabel": false,
					"invisible": false,
					"readonly": false,
					"disabled": true,
					"multiLine": false,
					"calculated": false,
					"linkCommand": null,
					"text": null,
					"group": null,
					"placeBeforeProperty": null,
					"placeAfterProperty": null,
					"decorators": [],
					"editorType": null
				},
				{
					"args": [
						32
					],
					"stateType": "default",
					"name": "CreatedDateTime",
					"bound": true,
					"commitChanges": false,
					"suppressLabel": false,
					"invisible": false,
					"readonly": false,
					"disabled": true,
					"multiLine": false,
					"calculated": false,
					"linkCommand": null,
					"text": null,
					"group": null,
					"placeBeforeProperty": null,
					"placeAfterProperty": null,
					"decorators": [],
					"editorType": null
				},
				{
					"args": null,
					"stateType": "default",
					"name": "HoldEntry",
					"bound": true,
					"commitChanges": false,
					"suppressLabel": false,
					"invisible": false,
					"readonly": false,
					"disabled": false,
					"multiLine": false,
					"calculated": false,
					"linkCommand": null,
					"text": null,
					"group": null,
					"placeBeforeProperty": null,
					"placeAfterProperty": null,
					"decorators": [],
					"editorType": null
				},
				{
					"args": [
						16
					],
					"stateType": "default",
					"name": "RequestApproval",
					"bound": true,
					"commitChanges": true,
					"suppressLabel": false,
					"invisible": false,
					"readonly": false,
					"disabled": false,
					"multiLine": false,
					"calculated": false,
					"linkCommand": null,
					"text": null,
					"group": null,
					"placeBeforeProperty": null,
					"placeAfterProperty": null,
					"decorators": [],
					"editorType": null
				},
				{
					"args": [
						16
					],
					"stateType": "default",
					"name": "ApprovalGroupID",
					"bound": true,
					"commitChanges": true,
					"suppressLabel": false,
					"invisible": false,
					"readonly": false,
					"disabled": false,
					"multiLine": false,
					"calculated": false,
					"linkCommand": null,
					"text": null,
					"group": null,
					"placeBeforeProperty": null,
					"placeAfterProperty": null,
					"decorators": [],
					"editorType": null
				},
				{
					"args": null,
					"stateType": "default",
					"name": "ApprovalUserID",
					"bound": true,
					"commitChanges": false,
					"suppressLabel": false,
					"invisible": false,
					"readonly": false,
					"disabled": false,
					"multiLine": false,
					"calculated": false,
					"linkCommand": null,
					"text": null,
					"group": null,
					"placeBeforeProperty": null,
					"placeAfterProperty": null,
					"decorators": [
						{
							"name": {
								"name": "selectorSettings"
							},
							"arguments": [
								"pkID",
								""
							]
						}
					],
					"editorType": null
				},
				{
					"args": null,
					"stateType": "default",
					"name": "IsActive",
					"bound": true,
					"commitChanges": false,
					"suppressLabel": false,
					"invisible": false,
					"readonly": false,
					"disabled": false,
					"multiLine": false,
					"calculated": false,
					"linkCommand": null,
					"text": null,
					"group": null,
					"placeBeforeProperty": null,
					"placeAfterProperty": null,
					"decorators": [],
					"editorType": null
				},
				{
					"args": [
						16
					],
					"stateType": "default",
					"name": "Category",
					"bound": true,
					"commitChanges": true,
					"suppressLabel": false,
					"invisible": false,
					"readonly": false,
					"disabled": false,
					"multiLine": false,
					"calculated": false,
					"linkCommand": null,
					"text": null,
					"group": null,
					"placeBeforeProperty": null,
					"placeAfterProperty": null,
					"decorators": [],
					"editorType": null
				},
				{
					"args": null,
					"stateType": "default",
					"name": "Position",
					"bound": true,
					"commitChanges": false,
					"suppressLabel": false,
					"invisible": false,
					"readonly": false,
					"disabled": false,
					"multiLine": false,
					"calculated": false,
					"linkCommand": null,
					"text": null,
					"group": null,
					"placeBeforeProperty": null,
					"placeAfterProperty": null,
					"decorators": [],
					"editorType": null
				},
				{
					"args": null,
					"stateType": "default",
					"name": "DefaultUrl",
					"bound": true,
					"commitChanges": false,
					"suppressLabel": false,
					"invisible": false,
					"readonly": false,
					"disabled": false,
					"multiLine": false,
					"calculated": false,
					"linkCommand": null,
					"text": null,
					"group": null,
					"placeBeforeProperty": null,
					"placeAfterProperty": null,
					"decorators": [],
					"editorType": null
				},
				{
					"args": [
						16
					],
					"stateType": "default",
					"name": "SitemapParent",
					"bound": true,
					"commitChanges": true,
					"suppressLabel": false,
					"invisible": false,
					"readonly": false,
					"disabled": false,
					"multiLine": false,
					"calculated": false,
					"linkCommand": null,
					"text": null,
					"group": null,
					"placeBeforeProperty": null,
					"placeAfterProperty": null,
					"decorators": [],
					"editorType": null
				},
				{
					"args": null,
					"stateType": "default",
					"name": "SitemapTitle",
					"bound": true,
					"commitChanges": false,
					"suppressLabel": false,
					"invisible": false,
					"readonly": false,
					"disabled": false,
					"multiLine": false,
					"calculated": false,
					"linkCommand": null,
					"text": null,
					"group": null,
					"placeBeforeProperty": null,
					"placeAfterProperty": null,
					"decorators": [],
					"editorType": null
				}
			],
			"extensions": [],
			"decorators": [
				{
					"name": {
						"name": "viewInfo"
					},
					"arguments": [
						{
							"containerName": "Wiki"
						}
					]
				}
			],
			"actions": []
		},
		{
			"name": "SiteMapTree",
			"dacClassName": null,
			"displayName": "Wiki",
			"isCollection": false,
			"featureInstalled": [],
			"fields": [],
			"extensions": [],
			"decorators": [
				{
					"name": {
						"name": "viewInfo"
					},
					"arguments": [
						{
							"containerName": "Wiki"
						}
					]
				}
			],
			"actions": []
		},
		{
			"name": "CurrentWiki",
			"dacClassName": null,
			"displayName": null,
			"isCollection": false,
			"featureInstalled": [],
			"fields": [
				{
					"args": [
						16
					],
					"stateType": "default",
					"name": "CssID",
					"bound": true,
					"commitChanges": true,
					"suppressLabel": false,
					"invisible": false,
					"readonly": false,
					"disabled": false,
					"multiLine": false,
					"calculated": false,
					"linkCommand": null,
					"text": null,
					"group": null,
					"placeBeforeProperty": null,
					"placeAfterProperty": null,
					"decorators": [],
					"editorType": null
				},
				{
					"args": null,
					"stateType": "default",
					"name": "CssPrintID",
					"bound": true,
					"commitChanges": false,
					"suppressLabel": false,
					"invisible": false,
					"readonly": false,
					"disabled": false,
					"multiLine": false,
					"calculated": false,
					"linkCommand": null,
					"text": null,
					"group": null,
					"placeBeforeProperty": null,
					"placeAfterProperty": null,
					"decorators": [],
					"editorType": null
				},
				{
					"args": [
						16
					],
					"stateType": "default",
					"name": "SPWikiArticleType",
					"bound": true,
					"commitChanges": true,
					"suppressLabel": false,
					"invisible": false,
					"readonly": false,
					"disabled": false,
					"multiLine": false,
					"calculated": false,
					"linkCommand": null,
					"text": null,
					"group": null,
					"placeBeforeProperty": null,
					"placeAfterProperty": null,
					"decorators": [],
					"editorType": null
				},
				{
					"args": null,
					"stateType": "default",
					"name": "RootPageID",
					"bound": true,
					"commitChanges": false,
					"suppressLabel": false,
					"invisible": false,
					"readonly": false,
					"disabled": false,
					"multiLine": false,
					"calculated": false,
					"linkCommand": null,
					"text": null,
					"group": null,
					"placeBeforeProperty": null,
					"placeAfterProperty": null,
					"decorators": [],
					"editorType": null
				},
				{
					"args": null,
					"stateType": "default",
					"name": "RootPrintPageID",
					"bound": true,
					"commitChanges": false,
					"suppressLabel": false,
					"invisible": false,
					"readonly": false,
					"disabled": false,
					"multiLine": false,
					"calculated": false,
					"linkCommand": null,
					"text": null,
					"group": null,
					"placeBeforeProperty": null,
					"placeAfterProperty": null,
					"decorators": [],
					"editorType": null
				},
				{
					"args": null,
					"stateType": "default",
					"name": "HeaderPageID",
					"bound": true,
					"commitChanges": false,
					"suppressLabel": false,
					"invisible": false,
					"readonly": false,
					"disabled": false,
					"multiLine": false,
					"calculated": false,
					"linkCommand": null,
					"text": null,
					"group": null,
					"placeBeforeProperty": null,
					"placeAfterProperty": null,
					"decorators": [],
					"editorType": null
				},
				{
					"args": null,
					"stateType": "default",
					"name": "FooterPageID",
					"bound": true,
					"commitChanges": false,
					"suppressLabel": false,
					"invisible": false,
					"readonly": false,
					"disabled": false,
					"multiLine": false,
					"calculated": false,
					"linkCommand": null,
					"text": null,
					"group": null,
					"placeBeforeProperty": null,
					"placeAfterProperty": null,
					"decorators": [],
					"editorType": null
				},
				{
					"args": null,
					"stateType": "default",
					"name": "SiteMapTagID",
					"bound": true,
					"commitChanges": false,
					"suppressLabel": false,
					"invisible": false,
					"readonly": false,
					"disabled": false,
					"multiLine": false,
					"calculated": false,
					"linkCommand": null,
					"text": null,
					"group": null,
					"placeBeforeProperty": null,
					"placeAfterProperty": null,
					"decorators": [],
					"editorType": null
				},
				{
					"args": null,
					"stateType": "default",
					"name": "PubVirtualPath",
					"bound": true,
					"commitChanges": false,
					"suppressLabel": false,
					"invisible": false,
					"readonly": false,
					"disabled": false,
					"multiLine": false,
					"calculated": false,
					"linkCommand": null,
					"text": null,
					"group": null,
					"placeBeforeProperty": null,
					"placeAfterProperty": null,
					"decorators": [],
					"editorType": null
				},
				{
					"args": [
						8
					],
					"stateType": "default",
					"name": "WikiDescription",
					"bound": true,
					"commitChanges": false,
					"suppressLabel": false,
					"invisible": false,
					"readonly": false,
					"disabled": false,
					"multiLine": true,
					"calculated": false,
					"linkCommand": null,
					"text": null,
					"group": null,
					"placeBeforeProperty": null,
					"placeAfterProperty": null,
					"decorators": [],
					"editorType": null
				}
			],
			"extensions": [],
			"decorators": [
				{
					"name": {
						"name": "viewInfo"
					},
					"arguments": [
						{
							"containerName": ""
						}
					]
				}
			],
			"actions": []
		},
		{
			"name": "EntityRoles",
			"dacClassName": null,
			"displayName": "Access Rights",
			"isCollection": true,
			"featureInstalled": [],
			"fields": [
				{
					"args": [
						2
					],
					"stateType": "default",
					"name": "ScreenID",
					"bound": true,
					"commitChanges": false,
					"suppressLabel": false,
					"invisible": true,
					"readonly": false,
					"disabled": false,
					"multiLine": false,
					"calculated": false,
					"linkCommand": null,
					"text": null,
					"group": null,
					"placeBeforeProperty": null,
					"placeAfterProperty": null,
					"decorators": [
						{
							"name": {
								"name": "columnConfig"
							},
							"arguments": [
								{
									"allowUpdate": false,
									"allowShowHide": "False"
								}
							]
						}
					],
					"editorType": null
				},
				{
					"args": [
						2
					],
					"stateType": "default",
					"name": "CacheName",
					"bound": true,
					"commitChanges": false,
					"suppressLabel": false,
					"invisible": true,
					"readonly": false,
					"disabled": false,
					"multiLine": false,
					"calculated": false,
					"linkCommand": null,
					"text": null,
					"group": null,
					"placeBeforeProperty": null,
					"placeAfterProperty": null,
					"decorators": [
						{
							"name": {
								"name": "columnConfig"
							},
							"arguments": [
								{
									"allowUpdate": false,
									"allowShowHide": "False"
								}
							]
						}
					],
					"editorType": null
				},
				{
					"args": [
						2
					],
					"stateType": "default",
					"name": "MemberName",
					"bound": true,
					"commitChanges": false,
					"suppressLabel": false,
					"invisible": true,
					"readonly": false,
					"disabled": false,
					"multiLine": false,
					"calculated": false,
					"linkCommand": null,
					"text": null,
					"group": null,
					"placeBeforeProperty": null,
					"placeAfterProperty": null,
					"decorators": [
						{
							"name": {
								"name": "columnConfig"
							},
							"arguments": [
								{
									"allowUpdate": false,
									"allowShowHide": "False"
								}
							]
						}
					],
					"editorType": null
				},
				{
					"args": null,
					"stateType": "default",
					"name": "RoleName",
					"bound": true,
					"commitChanges": false,
					"suppressLabel": false,
					"invisible": false,
					"readonly": false,
					"disabled": false,
					"multiLine": false,
					"calculated": false,
					"linkCommand": null,
					"text": null,
					"group": null,
					"placeBeforeProperty": null,
					"placeAfterProperty": null,
					"decorators": [
						{
							"name": {
								"name": "columnConfig"
							},
							"arguments": [
								{
									"allowUpdate": false
								}
							]
						}
					],
					"editorType": null
				},
				{
					"args": null,
					"stateType": "default",
					"name": "Guest",
					"bound": true,
					"commitChanges": false,
					"suppressLabel": false,
					"invisible": false,
					"readonly": false,
					"disabled": false,
					"multiLine": false,
					"calculated": false,
					"linkCommand": null,
					"text": null,
					"group": null,
					"placeBeforeProperty": null,
					"placeAfterProperty": null,
					"decorators": [
						{
							"name": {
								"name": "columnConfig"
							},
							"arguments": [
								{
									"allowUpdate": false
								}
							]
						}
					],
					"editorType": null
				},
				{
					"args": null,
					"stateType": "default",
					"name": "RoleDescr",
					"bound": true,
					"commitChanges": false,
					"suppressLabel": false,
					"invisible": false,
					"readonly": false,
					"disabled": false,
					"multiLine": false,
					"calculated": false,
					"linkCommand": null,
					"text": null,
					"group": null,
					"placeBeforeProperty": null,
					"placeAfterProperty": null,
					"decorators": [
						{
							"name": {
								"name": "columnConfig"
							},
							"arguments": [
								{
									"allowUpdate": false
								}
							]
						}
					],
					"editorType": null
				},
				{
					"args": null,
					"stateType": "default",
					"name": "RoleRight",
					"bound": true,
					"commitChanges": false,
					"suppressLabel": false,
					"invisible": false,
					"readonly": false,
					"disabled": false,
					"multiLine": false,
					"calculated": false,
					"linkCommand": null,
					"text": null,
					"group": null,
					"placeBeforeProperty": null,
					"placeAfterProperty": null,
					"decorators": [],
					"editorType": null
				}
			],
			"extensions": [],
			"decorators": [
				{
					"name": {
						"name": "viewInfo"
					},
					"arguments": [
						{
							"containerName": "Access Rights"
						}
					]
				},
				{
					"name": {
						"name": "gridConfig"
					},
					"arguments": [
						{
							"preset": "Details"
						}
					]
				}
			],
			"actions": []
		},
		{
			"name": "Tags",
			"dacClassName": null,
			"displayName": "Tags",
			"isCollection": true,
			"featureInstalled": [],
			"fields": [
				{
					"args": null,
					"stateType": "default",
					"name": "Description",
					"bound": true,
					"commitChanges": false,
					"suppressLabel": false,
					"invisible": false,
					"readonly": false,
					"disabled": false,
					"multiLine": false,
					"calculated": false,
					"linkCommand": null,
					"text": null,
					"group": null,
					"placeBeforeProperty": null,
					"placeAfterProperty": null,
					"decorators": [],
					"editorType": null
				}
			],
			"extensions": [],
			"decorators": [
				{
					"name": {
						"name": "viewInfo"
					},
					"arguments": [
						{
							"containerName": "Tags"
						}
					]
				},
				{
					"name": {
						"name": "gridConfig"
					},
					"arguments": [
						{
							"preset": "Details"
						}
					]
				}
			],
			"actions": [
				{
					"name": "processTag",
					"decorators": []
				}
			]
		},
		{
			"name": "ReadLangs",
			"dacClassName": null,
			"displayName": "Locales",
			"isCollection": true,
			"featureInstalled": [],
			"fields": [
				{
					"args": null,
					"stateType": "default",
					"name": "Selected",
					"bound": true,
					"commitChanges": false,
					"suppressLabel": false,
					"invisible": false,
					"readonly": false,
					"disabled": false,
					"multiLine": false,
					"calculated": false,
					"linkCommand": null,
					"text": null,
					"group": null,
					"placeBeforeProperty": null,
					"placeAfterProperty": null,
					"decorators": [],
					"editorType": null
				},
				{
					"args": null,
					"stateType": "default",
					"name": "Language",
					"bound": true,
					"commitChanges": false,
					"suppressLabel": false,
					"invisible": false,
					"readonly": false,
					"disabled": false,
					"multiLine": false,
					"calculated": false,
					"linkCommand": null,
					"text": null,
					"group": null,
					"placeBeforeProperty": null,
					"placeAfterProperty": null,
					"decorators": [],
					"editorType": null
				}
			],
			"extensions": [],
			"decorators": [
				{
					"name": {
						"name": "viewInfo"
					},
					"arguments": [
						{
							"containerName": "Locales"
						}
					]
				},
				{
					"name": {
						"name": "gridConfig"
					},
					"arguments": [
						{
							"preset": "Details",
							"allowDelete": false,
							"allowInsert": false
						}
					]
				}
			],
			"actions": [],
			"allowDelete": false,
			"allowInsert": false
		},
		{
			"name": "SitePaths",
			"dacClassName": null,
			"displayName": "File Paths",
			"isCollection": true,
			"featureInstalled": [],
			"fields": [
				{
					"args": null,
					"stateType": "default",
					"name": "PageName",
					"bound": true,
					"commitChanges": false,
					"suppressLabel": false,
					"invisible": false,
					"readonly": false,
					"disabled": false,
					"multiLine": false,
					"calculated": false,
					"linkCommand": null,
					"text": null,
					"group": null,
					"placeBeforeProperty": null,
					"placeAfterProperty": null,
					"decorators": [],
					"editorType": null
				},
				{
					"args": null,
					"stateType": "default",
					"name": "Path",
					"bound": true,
					"commitChanges": false,
					"suppressLabel": false,
					"invisible": false,
					"readonly": false,
					"disabled": false,
					"multiLine": false,
					"calculated": false,
					"linkCommand": null,
					"text": null,
					"group": null,
					"placeBeforeProperty": null,
					"placeAfterProperty": null,
					"decorators": [],
					"editorType": null
				}
			],
			"extensions": [],
			"decorators": [
				{
					"name": {
						"name": "viewInfo"
					},
					"arguments": [
						{
							"containerName": "File Paths"
						}
					]
				},
				{
					"name": {
						"name": "gridConfig"
					},
					"arguments": [
						{
							"preset": "Details"
						}
					]
				}
			],
			"actions": []
		}
	],
	"extensions": [],
	"decorators": [
		{
			"name": {
				"name": "graphInfo"
			},
			"arguments": [
				{
					"graphType": "PX.SM.WikiSetupMaint",
					"primaryView": "Wikis"
				}
			]
		}
	]
}