{"view":"SM208000","elements":[{"type":"QP-FIELDSET","id":"designsFieldset","elements":[{"type":"FIELD","id":"","name":"Designs.Name"}]},{"type":"QP-TABBAR","id":"mainTab","elements":[{"type":"QP-TAB","id":"TablesTab","elements":[{"type":"QP-GRID","id":"","view":"Tables","elements":[]}]},{"type":"QP-TAB","id":"RelationsTab","elements":[{"type":"QP-GRID","id":"","view":"Relations","elements":[]},{"type":"QP-GRID","id":"","view":"JoinConditions","elements":[{"type":"COLUMN","id":"","name":"OpenBrackets"},{"type":"COLUMN","id":"","name":"ParentField","controlType":"qp-formula-editor"},{"type":"COLUMN","id":"","name":"Condition"},{"type":"COLUMN","id":"","name":"ChildField","controlType":"qp-formula-editor"},{"type":"COLUMN","id":"","name":"CloseBrackets"},{"type":"COLUMN","id":"","name":"Operation"}]}]},{"type":"QP-TAB","id":"ResultsGridTab","elements":[{"type":"QP-FIELDSET","id":"currentDesignFieldset","elements":[{"type":"FIELD","id":"","name":"CurrentDesign.RowStyleFormula","controlType":"qp-formula-editor"}]},{"type":"QP-GRID","id":"","view":"Results","elements":[{"type":"COLUMN","id":"","name":"IsActive"},{"type":"COLUMN","id":"","name":"ObjectName"},{"type":"COLUMN","id":"","name":"Field","controlType":"qp-formula-editor"},{"type":"COLUMN","id":"","name":"SchemaField"},{"type":"COLUMN","id":"","name":"Width"},{"type":"COLUMN","id":"","name":"StyleFormula","controlType":"qp-formula-editor"},{"type":"COLUMN","id":"","name":"IsVisible"},{"type":"COLUMN","id":"","name":"DefaultNav"},{"type":"COLUMN","id":"","name":"NavigationNbr"}]}]},{"type":"QP-TAB","id":"NavigationTab","elements":[{"type":"QP-GRID","id":"","view":"NavigationScreens","elements":[]},{"type":"QP-GRID","id":"","view":"NavigationParameters","elements":[{"type":"COLUMN","id":"","name":"FieldName"},{"type":"COLUMN","id":"","name":"ParameterName","controlType":"qp-formula-editor"},{"type":"COLUMN","id":"","name":"IsExpression"},{"type":"COLUMN","id":"","name":"DesignID"},{"type":"COLUMN","id":"","name":"LineNbr"},{"type":"COLUMN","id":"","name":"NavigationScreenLineNbr"}]}]}]}]}