{"tabGeneral":{"caption":"General"},"tabHistory":{"caption":"History"},"tabFinancial":{"caption":"Financial"},"tabAttributes":{"caption":"Attributes"},"tabActivities":{"caption":"Activities"},"tabMailingPrinting":{"caption":"Mailing & Printing"},"tabWorkgroups":{"caption":"Workgroups"},"tabAssignmentandApprovalMaps":{"caption":"Assignment and Approval Maps"},"tabDelegates":{"caption":"Delegates"},"tabUser":{"caption":"User Info"},"tabCorporateCards":{"caption":"Corporate Cards"},"tabLaborItemOverrides":{"caption":"Labor Item Overrides"},"tabSkills":{"caption":"Skills"},"tabServiceAreas":{"caption":"Service Areas"},"tabLicenses":{"caption":"Licenses"},"GenTimeCardFilter":{"caption":"Generate Time Cards"},"btnOK":{"caption":"Generate"},"User":{"caption":"Change password"},"ChangeIDDialog":{"caption":"Specify New ID"},"tabFinancial_GLAccounts":{"caption":"GL Accounts"},"tabFinancial_FinancialSettings":{"caption":"Financial Settings"},"tabFinancial_PaymentSettings":{"caption":"Payment Settings"},"gridFinancial_PaymentDetails":{"caption":"Payment Instructions"},"tabGeneral_ContactInfo":{"caption":"Contact Info"},"tabGeneral_AddressInfo":{"caption":"Address info"},"tabGeneral_EmployeeSettings_Time":{"caption":"Employee Settings"},"tabGeneral_EmployeeSettings_Additional":{"caption":"Additional Settings"},"btnResetPassword":{"caption":"Reset Password"}}